<?xml version="1.0" encoding="utf-8"?>
<item xmlns="http://www.supermemo.net/2006/smux">
  <lesson-title>GRE词汇：《再要你命三千》</lesson-title>
  <chapter-title>List 4</chapter-title>
  <question-title>根据单词，回想词义</question-title>
  <question><span style="font-size:18; font-family:Comic Sans MS; font-weight:normal; font-style:normal; color:#550000">coma</span><br /><span style="font-size:14; font-family:微软雅黑; font-weight:normal; font-style:normal; color:#000000">[&lt;font face="Kingsoft Phonetic"&gt;5kEJmE&lt;/font&gt;]</span><br /></question>
  <answer>【考法 1】 n. 昏睡：a state of profound unconsciousness caused by disease, injury, or poison<br />
【例】The girl lay in a coma for three days after the accident.<br />
【近】insensibility, blackout, knockout<br />
【反】consciousness, awareness 有知觉<br />
<br />
【考法 2】 n. 迟钝，冷漠： a state of mental or physical sluggishness : torpor<br />
【近】sluggish, torpor<br />
【反】activity, animation 有活力；alacrity 敏捷<br />
<br />
【记】 comma “，”逗号代表停顿，思维意识停顿，逗号也象个coma彗星；音：磕懵<br />
<br />
<br />
</answer>
  <modified>2015-08-06</modified>
  <template-id>10004</template-id>
  <question-audio>true</question-audio>
</item>