<?xml version="1.0" encoding="utf-8"?>
<item xmlns="http://www.supermemo.net/2006/smux">
  <lesson-title>GRE词汇：《再要你命三千》</lesson-title>
  <chapter-title>List 24</chapter-title>
  <question-title>根据单词，回想词义</question-title>
  <question><span style='font-size:18; font-family:Comic Sans MS; font-weight:normal; font-style:normal; color:#550000'>sprightly</span><br/><span style='font-size:14; font-family:微软雅黑; font-weight:normal; font-style:normal; color:#000000'>[&lt;font face="Kingsoft Phonetic"&gt;5spraItlI&lt;/font&gt;]</span><br/></question>
  <answer>【考法 1】  adj. 活泼的，充满活力的：  full of spirit and vitality&lt;br&gt;【例】  He was deeply impressed by the sprightly Gypsy dance.  活力四射的吉普赛舞蹈给他留下了深刻印象。&lt;br&gt;【近】   active, airy, animated, brisk, energetic, frisky, gay, jaunty, kinetic, mettlesome, racy, spirited, vital, vivacious&lt;br&gt;【反】  dead, inactive, inanimate, lackadaisical, languid, languishing, leaden, lifeless, listless, spiritless, vapid 没精神的&lt;br&gt;&lt;br&gt;【记】  sprite的变体，源自spirit 精神，灵魂，勇气，热情；有精神头的；spring 春天 + bright 明亮欢快的<br/></answer>
  <question-audio>true</question-audio>
  <modified>2011-10-14</modified>
<template-id>10024</template-id>
</item>
