<?xml version="1.0" encoding="utf-8"?>
<item xmlns="http://www.supermemo.net/2006/smux">
  <lesson-title>GRE词汇：《再要你命三千》</lesson-title>
  <chapter-title>List 25</chapter-title>
  <question-title>根据单词，回想词义</question-title>
  <question><span style='font-size:18; font-family:Comic Sans MS; font-weight:normal; font-style:normal; color:#550000'>talisman</span><br/><span style='font-size:14; font-family:微软雅黑; font-weight:normal; font-style:normal; color:#000000'>[&lt;font face="Kingsoft Phonetic"&gt;5tAlizmEn&lt;/font&gt;]</span><br/></question>
  <answer>【考法 1】  n. 护身符：  something worn or kept to bring good luck or keep away evil&lt;br&gt;【例】  A pendant of white nephrite jade is often worn by Indians as a talisman to ward off heart disease.  印度人通常戴一串软玉项链防止心脏病发作。&lt;br&gt;【近】  amulet, fetish, mascot, mojo, periapt, phylactery&lt;br&gt;&lt;br&gt;【记】  tale + man 传说中的人物，有许多人拿传说中的人物作护身符，玉观音，玉佛或十字架之类的作护身符&lt;br&gt;【另】  amulet 护身符<br/></answer>
  <question-audio>true</question-audio>
  <modified>2011-10-14</modified>
<template-id>10025</template-id>
</item>
