<?xml version="1.0" encoding="utf-8"?>
<item xmlns="http://www.supermemo.net/2006/smux">
  <lesson-title>GRE词汇：《再要你命三千》</lesson-title>
  <chapter-title>List 8</chapter-title>
  <question-title>根据单词，回想词义</question-title>
  <question><span style="font-size:18; font-family:Comic Sans MS; font-weight:normal; font-style:normal; color:#550000">effete</span><br /><span style="font-size:14; font-family:微软雅黑; font-weight:normal; font-style:normal; color:#000000">[&lt;font face="Kingsoft Phonetic"&gt;e5fi:t&lt;/font&gt;]</span><br /></question>
  <answer>【考法 1】 adj. 衰弱的： depleted of vitality, force, or effectiveness<br />
【例】 an effete monarchy['mɑnɚki]君主制<br />
【近】 consumed, debilitated, decadent, degenerate, depleted, drained喝光，喝干；使（精力、金钱等）耗尽, exhausted, feeble<br />
【反】 hale, sound, robust 强健的，充满活力的<br />
<br />
【考法 2】 adj. 懦弱的： lacking strength of will or character<br />
【例】 The government is too effete to take out the powerful special interests利益 that really ruin this state.<br />
【近】 frail, invertebrate, nerveless, spineless<br />
【反】 backboned, firm, hard, strong, tough 刚毅的<br />
【派】 effetely adv. 衰弱地<br />
<br />
【记】 ef (ex) 不 + fetus 胎儿，再也生不出小孩了→不能再生产了，精疲力竭的，虚弱的，柔弱的；ef<br />
+ feet 再也迈不动脚了，精疲力竭，虚弱了<br />
</answer>
  <modified>2015-08-25</modified>
  <template-id>10008</template-id>
  <question-audio>true</question-audio>
</item>