<?xml version="1.0" encoding="utf-8"?>
<item xmlns="http://www.supermemo.net/2006/smux">
  <lesson-title>GRE词汇：《再要你命三千》</lesson-title>
  <chapter-title>List 4</chapter-title>
  <question-title>根据单词，回想词义</question-title>
  <question><span style="font-family: Comic Sans MS; font-weight: normal; color: #550000; font-style: normal">cloying</span><br />
<span style="font-family: 微软雅黑; font-weight: normal; color: #000000; font-style: normal">['klɔɪɪŋ]</span></question>
  <answer>【考法 1】 adj. 甜得发腻的，感情用事的：excessively sweet or sentimental<br />
【例】Sugar becomes cloying; <span><br />
</span>【近】lovey-dovey, maudlin, mawkish, saccharine['sækəraɪn;]极甜的；和颜悦色的, sentimental多愁善感的；感情用事的<br />
【反】unsentimental<br />
【例】the cloying sentiments of so many Mother's Day cards 这么多母亲节贺卡（所蕴含）的甜蜜感情<br />
<br />
【记】 cloy + ing<br />
<br />
<br />
<br />
<br />
</answer>
  <modified>2015-08-27</modified>
  <template-id>10004</template-id>
  <question-audio>true</question-audio>
</item>