<?xml version="1.0" encoding="utf-8"?>
<item xmlns="http://www.supermemo.net/2006/smux">
  <lesson-title>GRE词汇：《再要你命三千》</lesson-title>
  <chapter-title>List 16</chapter-title>
  <question-title>根据单词，回想词义</question-title>
  <question><span style='font-size:18; font-family:Comic Sans MS; font-weight:normal; font-style:normal; color:#550000'>miserly</span><br/><span style='font-size:14; font-family:微软雅黑; font-weight:normal; font-style:normal; color:#000000'>[&lt;font face="Kingsoft Phonetic"&gt;5maizEli&lt;/font&gt;]</span><br/></question>
  <answer>【考法 1】  adj. 吝啬的：  marked by grasping meanness and penuriousness&lt;br&gt;【例】  a miserly couple devoid of social conscience and responsibility  一对没有社会良心和责任感的吝啬夫妻&lt;br&gt;【近】  closefisted, mean, niggard, parsimonious, penurious, stingy, tightfisted&lt;br&gt;【反】  lavish, prodigal, spendthrift, squandering  浪费的；generous, liberal, munificent, openhanded  慷慨的&lt;br&gt;【派】  miser  n. 守财奴&lt;br&gt;&lt;br&gt;【记】  miser<br/></answer>
  <question-audio>true</question-audio>
  <modified>2011-10-14</modified>
<template-id>10016</template-id>
</item>
