<?xml version="1.0" encoding="utf-8"?>
<item xmlns="http://www.supermemo.net/2006/smux">
  <lesson-title>GRE词汇：《再要你命三千》</lesson-title>
  <chapter-title>List 29</chapter-title>
  <question-title>根据单词，回想词义</question-title>
  <question><span style='font-size:18; font-family:Comic Sans MS; font-weight:normal; font-style:normal; color:#550000'>brandish</span><br/><span style='font-size:14; font-family:微软雅黑; font-weight:normal; font-style:normal; color:#000000'>[&lt;font face="Kingsoft Phonetic"&gt;5brAndiF&lt;/font&gt;]</span><br/></question>
  <answer>【考法 1】  vt. （带有威胁性地）挥舞：  to shake or wave (as a weapon) menacingly&lt;br&gt;【例】  I could see that the suspect was brandishing a knife and was in no way inclined to surrender.  我可以看到嫌犯在挥舞着一把刀，完全没有要投降的倾向。&lt;br&gt;【近】  shake, swing, wave&lt;br&gt;【反】  drop 放下（武器等）&lt;br&gt;&lt;br&gt;【记】  brandy 白兰地 + dish 菜，菜桌上有人拿着瓶白兰地威胁地挥舞着(要与你拼酒)；brand 商标&lt;br&gt;，品牌 + dish 菜，招牌菜，威胁性地挥舞着招牌(让人进饭馆吃菜)<br/></answer>
  <question-audio>true</question-audio>
  <modified>2011-10-14</modified>
<template-id>10029</template-id>
</item>
