<?xml version="1.0" encoding="utf-8"?>
<item xmlns="http://www.supermemo.net/2006/smux">
  <lesson-title>GRE词汇：《再要你命三千》</lesson-title>
  <chapter-title>List 19</chapter-title>
  <question-title>根据单词，回想词义</question-title>
  <question><span style='font-size:18; font-family:Comic Sans MS; font-weight:normal; font-style:normal; color:#550000'>primp</span><br/><span style='font-size:14; font-family:微软雅黑; font-weight:normal; font-style:normal; color:#000000'>[&lt;font face="Kingsoft Phonetic"&gt;primp&lt;/font&gt;]</span><br/></question>
  <answer>【考法 1】  v. 精心打扮：  to dress, adorn, or arrange in a careful or finicky manner&lt;br&gt;【例】  She primps for hours before a date.  她出门约会前要花数小时打扮。&lt;br&gt;【近】  preen, dress up&lt;br&gt;&lt;br&gt;【记】  来自prim整洁 + 音：扑，扑粉；prime 一流的 + p 音：漂，漂亮；音：漂亮美婆，音近&lt;br&gt;plump，后者lump身上肿块，胖的<br/></answer>
  <question-audio>true</question-audio>
  <modified>2011-10-14</modified>
<template-id>10019</template-id>
</item>
