<?xml version="1.0" encoding="utf-8"?>
<item xmlns="http://www.supermemo.net/2006/smux">
  <lesson-title>GRE词汇：《再要你命三千》</lesson-title>
  <chapter-title>List 31</chapter-title>
  <question-title>根据单词，回想词义</question-title>
  <question><span style='font-size:18; font-family:Comic Sans MS; font-weight:normal; font-style:normal; color:#550000'>project</span><br/><span style='font-size:14; font-family:微软雅黑; font-weight:normal; font-style:normal; color:#000000'>[&lt;font face="Kingsoft Phonetic"&gt;prE5dVekt&lt;/font&gt;]</span><br/></question>
  <answer>【考法 1】  n. 方案，计划：  a specific plan or design&lt;br&gt;【例】  an ambitious project to develop the city’s underground transport 一项开发城市地下交通系统的雄心勃勃的计划&lt;br&gt;【近】  arrangement, blueprint, design, plan, program, scheme, strategy, system, road map&lt;br&gt;&lt;br&gt;【考法 2】  vi. 凸出：  to extend outward beyond a usual point&lt;br&gt;【例】  Some boulders projected dangerously out above the trail.  一些巨石非常危险地在道路上凸了出来。&lt;br&gt;【近】  balloon, beetle, billow, bunch, jut, overhang, poke, pouch, pout, protrude, swell&lt;br&gt;&lt;br&gt;【考法 3】   vt. 预测，预计：   to calculate, estimate, or predict (something in the future), based on present data or trends&lt;br&gt;【例】  projecting next year’s expenses 预测明年的开销&lt;br&gt;【近】  augur, estimate, extrapolate, forecast, predict, predetermine, presage&lt;br&gt;【派】  projected  adj. 计划的；projection  n. 凸起物；投影 &lt;br&gt;&lt;br&gt;<br/></answer>
  <question-audio>true</question-audio>
  <modified>2011-10-14</modified>
<template-id>10031</template-id>
</item>
