<?xml version="1.0" encoding="utf-8"?>
<item xmlns="http://www.supermemo.net/2006/smux">
  <lesson-title>GRE词汇：《再要你命三千》</lesson-title>
  <chapter-title>List 5</chapter-title>
  <question-title>根据单词，回想词义</question-title>
  <question><span style="font-size:18; font-family:Comic Sans MS; font-weight:normal; font-style:normal; color:#550000">content</span><br /><span style="font-size:14; font-family:微软雅黑; font-weight:normal; font-style:normal; color:#000000">[&lt;font face="Kingsoft Phonetic"&gt;5kRntent&lt;/font&gt;]</span><br /></question>
  <answer>【考法 1】 v. 使满足： to appease the desires of<br />
【例】 One glass of beer every day could content him.<br />
【近】 satisfy, gratify, rejoice<br />
【反】 discontent 不满足<br />
<br />
【考法 2】 n. 主题： a major object of interest or concern (as in a discussion or artistic composition)<br />
【例】 Although I appreciate the poem's lyrical qualities, I don't understand its content. 虽然我很欣赏这首诗歌的节奏美，但我无法理解其主题<br />
【近】 motive, subject, theme, topic<br />
<br />
【考法 3】 n. 内容，内涵： the idea that is conveyed or intended to be conveyed to the mind by language, symbol, or action<br />
【例】 The speech was filled with fancy words but devoid of any real content. 这篇演讲辞藻华丽，但是没什么实质性内容<br />
【近】 intention, purport['pɝpɔt], sense, significance<br />
【派】 contented adj. 满足的<br />
<br />
【记】 源自contain 包含，包含的是容量，内容，满足。内容抵达容量，就是满足<br />
</answer>
  <modified>2015-08-24</modified>
  <template-id>10005</template-id>
  <question-audio>true</question-audio>
</item>