<?xml version="1.0" encoding="utf-8"?>
<item xmlns="http://www.supermemo.net/2006/smux">
  <lesson-title>GRE词汇：《再要你命三千》</lesson-title>
  <chapter-title>List 16</chapter-title>
  <question-title>根据单词，回想词义</question-title>
  <question><span style='font-size:18; font-family:Comic Sans MS; font-weight:normal; font-style:normal; color:#550000'>noxious</span><br/><span style='font-size:14; font-family:微软雅黑; font-weight:normal; font-style:normal; color:#000000'>[&lt;font face="Kingsoft Phonetic"&gt;5nCkFEs&lt;/font&gt;]</span><br/></question>
  <answer>【考法 1】  adj. 有害的，有毒的：  harmful to living things; injurious to health&lt;br&gt;【例】  noxious waste 有害的废弃物&lt;br&gt;【近】  unwholesome, baneful, deleterious, detrimental, nocuous, pernicious, wicked&lt;br&gt;【反】 beneficial, salubrious, anodyne, benign, harmless, hurtless, innocent, innocuous, inoffensive, safe  有益的，无害的&lt;br&gt;&lt;br&gt;【考法 2】  adj. 产生强烈厌恶的：  causing intense displeasure, disgust, or resentment&lt;br&gt;【例】  a noxious new breed of horror movie in which graphic depictions of torture are presented as entertainment在一部新的恐怖电影中，对于酷刑生动的描述被当做是娱乐&lt;br&gt;【近】  abhorrent, abominable, appalling, awful, disgusting, distasteful, dreadful, foul, fulsome, gross, hideous, horrid, loathsome, nasty, nauseating, noisome, obnoxious, odious, repellent, repugnant, repulsive, revolting, scandalous&lt;br&gt;&lt;br&gt;【记】  近于necr- 死；同nocuous 有害的；熟悉的innocent就是无害的：in 无 + noc-害，&lt;br&gt;【另】  nocuous 有害的, 有毒的，innocent 无害的，清白的, 无罪的, 天真的；toxic(音：毒素) 有毒的<br/></answer>
  <question-audio>true</question-audio>
  <modified>2011-10-14</modified>
<template-id>10016</template-id>
</item>
