<?xml version="1.0" encoding="utf-8"?>
<item xmlns="http://www.supermemo.net/2006/smux">
  <lesson-title>GRE词汇：《再要你命三千》</lesson-title>
  <chapter-title>List 2</chapter-title>
  <question-title>根据单词，回想词义</question-title>
  <question><span style="font-size:18; font-family:Comic Sans MS; font-weight:normal; font-style:normal; color:#550000">babble</span><br /><span style="font-size:14; font-family:微软雅黑; font-weight:normal; font-style:normal; color:#000000">[&lt;font face="Kingsoft Phonetic"&gt;5bAbl&lt;/font&gt;]</span><br /></question>
  <answer>【考法 1】 v. 发出含糊无意义的嘟囔声，胡乱说： to utter a meaningless confusion of words or sounds<br />
【例】 Babies babble before they can talk. 婴儿在会说话以前含糊不清地发音<br />
【近】 drivel, gabble, gibber['dʒɪbə], jabber['dʒæbə], prattle, abracadabra[,æbrəkə'dæbrə]<br />
【反】 articulate 清晰地说出<br />
<br />
【考法 2】 v. 闲聊： to engage in casual or rambling conversation<br />
【例】 The little girls babbled contentedly for the whole ride home. 两个小姑娘在回家的路上高兴地闲聊<br />
【近】 chatter, prate[preɪt]<br />
<br />
【记】 baby 婴儿般学语声；bubble 泡泡声<br />
</answer>
  <modified>2015-08-04</modified>
  <template-id>10002</template-id>
  <question-audio>true</question-audio>
</item>