<?xml version="1.0" encoding="utf-8"?>
<item xmlns="http://www.supermemo.net/2006/smux">
  <lesson-title>GRE词汇：《再要你命三千》</lesson-title>
  <chapter-title>List 7</chapter-title>
  <question-title>根据单词，回想词义</question-title>
  <question><span style="font-size:18; font-family:Comic Sans MS; font-weight:normal; font-style:normal; color:#550000">dissolve</span><br /><span style="font-size:14; font-family:微软雅黑; font-weight:normal; font-style:normal; color:#000000">[&lt;font face="Kingsoft Phonetic"&gt;dI5zRlv&lt;/font&gt;]</span><br /></question>
  <answer>【考法 1】 v. 溶解，融化： to cause to pass into solution; to reduce (solid matter) to liquid form; melt<br />
【例】 Sugar dissolves in the water. 糖在水中溶解<br />
【近】 liquefy['lɪkwɪfaɪ], melt<br />
【反】 coagulate, solidify, freeze 凝结，凝固，结冰<br />
<br />
【考法 2】 vt. 解散： to break into component parts; disintegrate<br />
【近】 disintegrate, disband, break up<br />
【反】 consolidate, unify 使联合<br />
<br />
【考法 3】 v. 废除，撤销： to put an end to by formal action<br />
【例】 The king dissolved parliament['pɑrləmənt]. 国王废除了议会<br />
【近】 terminate, abrogate, annul, cancel, disannul, invalidate, negate, null, nullify, repeal, rescind<br />
<br />
【考法 4】 v. 消失： to cease to be visible; to cease to exist<br />
【例】 The mist dissolved in the morning sun. 雾消失在朝阳中。<br />
【近】 dematerialize, vanish<br />
【反】 appear 出现；materialize 使实物化<br />
<br />
<br />
【记】 dis 四周散 + solve 解决<br />
【另】 solve 解决<br />
<br />
<br />
</answer>
  <modified>2015-08-03</modified>
  <template-id>10007</template-id>
  <question-audio>true</question-audio>
</item>