<?xml version="1.0" encoding="utf-8"?>
<item xmlns="http://www.supermemo.net/2006/smux">
  <lesson-title>GRE词汇：《再要你命三千》</lesson-title>
  <chapter-title>List 2</chapter-title>
  <question-title>根据单词，回想词义</question-title>
  <question><span style="font-size:18; font-family:Comic Sans MS; font-weight:normal; font-style:normal; color:#550000">balm</span><br /><span style="font-size:14; font-family:微软雅黑; font-weight:normal; font-style:normal; color:#000000">[&lt;font face="Kingsoft Phonetic"&gt;bB:m&lt;/font&gt;]</span><br /></question>
  <answer>【考法 1】 n. 香油，止痛膏，安慰物： a sweet-smelling oil that heals wounds or reduce pain<br />
【例】 Friendship is the finest balm in need. 危难关头，友情是最好的安慰<br />
【反】 irritant 刺激物<br />
【派】 balmy adj. 柔和的<br />
<br />
【考法 2】 n. 香气： a sweet or pleasant smell<br />
【例】 The balm of the restaurant's backyard garden enhances the aura['ɔːrə] of romance. 餐馆后院传来的阵阵芳香增加了浪漫的情调<br />
【近】 aroma, fragrance, incense, perfume, redolence<br />
【反】 fetor, malodor, stench, stink 恶臭<br />
<br />
【记】 音：包抹，身上起了个包，抹点止痛的香膏；使你calm的东西：palm, psalm 手掌的爱抚，圣歌，与止痛药膏，香脂<br />
【另】 barm 酵母；palm..音：抛，摸，抛，摸东西都得用手palm；palm也是一著名掌上电脑品牌<br />
</answer>
  <modified>2015-07-20</modified>
  <template-id>10002</template-id>
  <question-audio>true</question-audio>
</item>