<?xml version="1.0" encoding="utf-8"?>
<item xmlns="http://www.supermemo.net/2006/smux">
  <lesson-title>GRE词汇：《再要你命三千》</lesson-title>
  <chapter-title>List 28</chapter-title>
  <question-title>根据单词，回想词义</question-title>
  <question><span style='font-size:18; font-family:Comic Sans MS; font-weight:normal; font-style:normal; color:#550000'>grit</span><br/><span style='font-size:14; font-family:微软雅黑; font-weight:normal; font-style:normal; color:#000000'>[&lt;font face="Kingsoft Phonetic"&gt;grIt&lt;/font&gt;]</span><br/></question>
  <answer>【考法 1】  n. （面对困难时所表现出来的）毅力：  the strength of mind that enables a person to endure pain or hardship&lt;br&gt;【例】  She was an athlete with true grit, continuing her training despite bad weather and an injury. 她是真正一个有着惊人毅力的运动员，即便是在受了伤外加天气恶劣的情况下仍然坚持训练。&lt;br&gt;【近】  backbone, constancy, fiber, grittiness, guts, intestinal fortitude, pluck, spunk&lt;br&gt;【反】  cowardliness, cravenness, gutlessness, pusillanimity, spinelessness 懦弱&lt;br&gt;&lt;br&gt;【记】  近于grain 颗粒，砂粒；great 要当伟人，伟大的事需要决心勇气咬紧牙关；grate 磨碎成颗粒&lt;br&gt;，磨牙磨得咯吱响，咬紧牙关；象砂粒一样坚硬，且咬紧牙关，表示决心与意志坚定，面临困难或危险时不屈的勇气；i=e, GRE it, 搞定GRE需要不怕苦，像沙石一样坚固的信念&lt;br&gt;【另】  grind 磨<br/></answer>
  <question-audio>true</question-audio>
  <modified>2011-10-14</modified>
<template-id>10028</template-id>
</item>
