<?xml version="1.0" encoding="utf-8"?>
<item xmlns="http://www.supermemo.net/2006/smux">
  <question-title>根据单词，回想词义 </question-title>
  <question>countervail<br />
[ˈkaʊntərveɪl]</question>
  <answer>【考法】 vt. 抗衡，抵消: to exert force against; counteract<br />
【例】 The extent to which these various unknown factors countervail each other remains uncertain. 这些未知因素彼此之间的抗衡程度仍无法确定。<br />
【近】 compensate, counteract, counterbalance, counterpoise, neutralize, offset<br />
【派】 countervailing  adj. 抗衡的，抵消的</answer>
  <modified>2014-02-02</modified>
  <template-id>10031</template-id>
  <question-audio>true</question-audio>
</item>