<?xml version="1.0" encoding="utf-8"?>
<item xmlns="http://www.supermemo.net/2006/smux">
  <lesson-title>GRE词汇：《再要你命三千》</lesson-title>
  <chapter-title>List 6</chapter-title>
  <question-title>根据单词，回想词义</question-title>
  <question><span style="font-size:18; font-family:Comic Sans MS; font-weight:normal; font-style:normal; color:#550000">daunt</span><br /><span style="font-size:14; font-family:微软雅黑; font-weight:normal; font-style:normal; color:#000000">[&lt;font face="Kingsoft Phonetic"&gt;dC:nt&lt;/font&gt;]</span><br /></question>
  <answer>【考法 1】 vt. 恐吓： to lessen the courage or confidence of<br />
【例】 She was not at all daunted by the size of the problem. 她根本没有被问题的大小给吓倒。<br />
【近】 demoralize, dishearten[dɪs'hɑːt(ə)n] , dismay, dispirit, frustrate, unnerve<br />
【反】 embolden, make resolute, hearten 使大胆，鼓舞<br />
【派】 dauntless undaunted a. 无畏的，大胆的<br />
【反】 pusillanimous, trepid, craven, easily discouraged, meek, timorous 胆怯的<br />
<br />
【记】 down it，down它，把它制下去，让它气势，胆气下去；音：倒塌，世贸大楼倒塌令人胆怯；音：打 + aunt→打姨妈→使胆怯<br />
Every advantage has its disadvantage.　　有利必有弊。<br />
</answer>
  <modified>2015-08-07</modified>
  <template-id>10006</template-id>
  <question-audio>true</question-audio>
</item>