<?xml version="1.0" encoding="utf-8"?>
<item xmlns="http://www.supermemo.net/2006/smux">
  <lesson-title>GRE词汇：《再要你命三千》</lesson-title>
  <chapter-title>List 27</chapter-title>
  <question-title>根据单词，回想词义</question-title>
  <question><span style='font-size:18; font-family:Comic Sans MS; font-weight:normal; font-style:normal; color:#550000'>viable</span><br/><span style='font-size:14; font-family:微软雅黑; font-weight:normal; font-style:normal; color:#000000'>[&lt;font face="Kingsoft Phonetic"&gt;5vaIEb(E)l&lt;/font&gt;]</span><br/></question>
  <answer>【考法 1】  adj. 可行的：  capable of being done or carried out&lt;br&gt;【例】  a viable solution to the problem  解决问题的一个可行方案&lt;br&gt;【近】  achievable, attainable, doable, feasible, practicable, realizable, workable&lt;br&gt;【反】  hopeless, impossible, impracticable, infeasible, unattainable, unviable, unworkable 不可行的&lt;br&gt;【派】  viability  n. 可行性&lt;br&gt;&lt;br&gt;【记】  源自vit- 生命，survive, live；via 通过 + ble 能通过的，过得去，可行的，能活的<br/></answer>
  <question-audio>true</question-audio>
  <modified>2011-10-14</modified>
<template-id>10027</template-id>
</item>
