<?xml version="1.0" encoding="utf-8"?>
<item xmlns="http://www.supermemo.net/2006/smux">
  <lesson-title>GRE词汇：《再要你命三千》</lesson-title>
  <chapter-title>List 5</chapter-title>
  <question-title>根据单词，回想词义</question-title>
  <question><span style="font-size:18; font-family:Comic Sans MS; font-weight:normal; font-style:normal; color:#550000">condign</span><br /><span style="font-size:14; font-family:微软雅黑; font-weight:normal; font-style:normal; color:#000000">[&lt;font face="Kingsoft Phonetic"&gt;kEn5daIn&lt;/font&gt;]</span><br /></question>
  <answer>【考法 1】 adj. 应得的，恰当的：deserved, appropriate<br />
【例】condign punishment 应得的惩罚<span><br />
</span>【例】A suspension停职 without pay is condign punishment for breaking the company's code of business ethics <br />
【近】due, deserved, merited['merɪtɪd, justified, warranted<br />
【反】undeserved, undue, unmerited 不应得的<br />
<br />
【记】 con + dignity 大家都有面子，适宜的<br />
<br />
<br />
</answer>
  <modified>2015-08-04</modified>
  <template-id>10005</template-id>
  <question-audio>true</question-audio>
</item>