<?xml version="1.0" encoding="utf-8"?>
<item xmlns="http://www.supermemo.net/2006/smux">
  <lesson-title>GRE词汇：《再要你命三千》</lesson-title>
  <chapter-title>List 17</chapter-title>
  <question-title>根据单词，回想词义</question-title>
  <question><span style='font-size:18; font-family:Comic Sans MS; font-weight:normal; font-style:normal; color:#550000'>paean</span><br/><span style='font-size:14; font-family:微软雅黑; font-weight:normal; font-style:normal; color:#000000'>[&lt;font face="Kingsoft Phonetic"&gt;5pi:En&lt;/font&gt;]</span><br/></question>
  <answer>【考法 1】  n. 欢乐颂：  a joyous song or hymn of praise, tribute, thanksgiving, or triumph&lt;br&gt;【例】  her retirement party featured many paeans for her long years of service to the company  她的退休派对满是对她多年在公司辛勤工作的赞颂&lt;br&gt;【近】 accolade, citation, dithyramb, eulogium, eulogy, hymn, panegyric, tribute&lt;br&gt;&lt;br&gt;【记】  音：拼音，用拼音来唱赞歌(因为是古希腊语，只会用拼音唱)；古希腊感恩的一种赞美诗,赞歌，尤指对太阳神&lt;br&gt;【另】  piety 虔诚<br/></answer>
  <question-audio>true</question-audio>
  <modified>2011-10-14</modified>
<template-id>10017</template-id>
</item>
