<?xml version="1.0" encoding="utf-8"?>
<item xmlns="http://www.supermemo.net/2006/smux">
  <lesson-title>GRE词汇：《再要你命三千》</lesson-title>
  <chapter-title>List 3</chapter-title>
  <question-title>根据单词，回想词义</question-title>
  <question><span style='font-size:18; font-family:Comic Sans MS; font-weight:normal; font-style:normal; color:#550000'>cache</span><br/><span style='font-size:14; font-family:微软雅黑; font-weight:normal; font-style:normal; color:#000000'>[&lt;font face="Kingsoft Phonetic"&gt;kAF&lt;/font&gt;]</span><br/></question>
  <answer>【考法 1】  n. 囤货，藏货：  a supply stored up and often hidden away&lt;br&gt;【例】  maintain a cache of food in case of emergencies  保存着食物的隐藏处以防万一&lt;br&gt;【近】  stash, stockpile, store, deposit, hoard, reserve&lt;br&gt;&lt;br&gt;【考法 2】  v. 隐藏：  to put into a hiding place&lt;br&gt;【例】  cached the fugitive slaves in their cellar until they could make their way to Canada 将奴隶们藏匿在房间的地下室直到他们能够顺利逃去加拿大&lt;br&gt;【近】  conceal, ensconce, secrete, squirrel away&lt;br&gt;【反】  display, exhibit  展示&lt;br&gt;&lt;br&gt;【记】  秘密贮藏cash的地方<br/></answer>
  <question-audio>true</question-audio>
  <modified>2011-10-14</modified>
<template-id>10003</template-id>
</item>
