<?xml version="1.0" encoding="utf-8"?>
<item xmlns="http://www.supermemo.net/2006/smux">
  <lesson-title>GRE词汇：《再要你命三千》</lesson-title>
  <chapter-title>List 4</chapter-title>
  <question-title>根据单词，回想词义</question-title>
  <question><span style='font-size:18; font-family:Comic Sans MS; font-weight:normal; font-style:normal; color:#550000'>compendium</span><br/><span style='font-size:14; font-family:微软雅黑; font-weight:normal; font-style:normal; color:#000000'>[&lt;font face="Kingsoft Phonetic"&gt;kEm5pendIEm&lt;/font&gt;]</span><br/></question>
  <answer>【考法 1】  n. 摘要：a brief summary of a larger work or of a field of knowledge: abstract&lt;br&gt;【例】a compendium of information  资料概要&lt;br&gt;【近】abstract, brief, overview&lt;br&gt;【派】compendious adj. 简洁而全面的：concise and comprehensive&lt;br&gt;【例】his compendious knowledge of this subject 他关于这一学科全面的知识&lt;br&gt;【近】concise, brief, laconic, compendiary, succinct&lt;br&gt;&lt;br&gt;【考法 2】 目录：各种项目的列表或集合：a list or collection of various items.&lt;br&gt;【例】Compendium of Materia Medica  《本草纲目》&lt;br&gt;【近】compilation, miscellany&lt;br&gt;&lt;br&gt;【记】  compendious<br/></answer>
  <question-audio>true</question-audio>
  <modified>2011-10-14</modified>
<template-id>10004</template-id>
</item>
