<?xml version="1.0" encoding="utf-8"?>
<item xmlns="http://www.supermemo.net/2006/smux">
  <lesson-title>GRE词汇：《再要你命三千》</lesson-title>
  <chapter-title>List 3</chapter-title>
  <question-title>根据单词，回想词义</question-title>
  <question><span style="font-family: Comic Sans MS; font-weight: normal; color: #550000; font-style: normal">camaraderie</span><br />
<span style="font-family: 微软雅黑; font-weight: normal; color: #000000; font-style: normal"><span style="color: #550000;">[,kɑmə'rɑdəri]</span></span><br />
</question>
  <answer>【考法 1】  n. 友情：  a spirit of friendly good-fellowship&lt;br&gt;【例】  There is great camaraderie among the teammates.  组员之间有着深厚的情谊。&lt;br&gt;【近】  brotherhood, comradeship, fellowship&lt;br&gt;【反】  enmity  敌意&lt;br&gt;&lt;br&gt;【记】  comrade 朋友<br /></answer>
  <modified>2015-07-20</modified>
  <template-id>10003</template-id>
  <question-audio>true</question-audio>
</item>