<?xml version="1.0" encoding="utf-8"?>
<item xmlns="http://www.supermemo.net/2006/smux">
  <lesson-title>GRE词汇：《再要你命三千》</lesson-title>
  <chapter-title>List 10</chapter-title>
  <question-title>根据单词，回想词义</question-title>
  <question><span style="font-size:18; font-family:Comic Sans MS; font-weight:normal; font-style:normal; color:#550000">fervor</span><br /><span style="font-size:14; font-family:微软雅黑; font-weight:normal; font-style:normal; color:#000000">[&lt;font face="Kingsoft Phonetic"&gt;5f\:vE&lt;/font&gt;]</span><br /></question>
  <answer>【考法 1】 n. 热情，狂热： great warmth and intensity of emotion<br />
【例】 A blind patriotic[peɪtri'ɒtɪk]爱国的 fervor is called chauvinism. 盲目的爱国热情就被称为沙文主义<br />
【近】 ardor, enthusiasm, passion, zeal, zealotry<br />
【反】 apathy, indifference, impassiveness, unconcern 冷漠<br />
<br />
【记】 fever 发烧<br />
</answer>
  <modified>2015-08-02</modified>
  <template-id>10010</template-id>
  <question-audio>true</question-audio>
</item>